justcode/__init__.py
justcode/justcode.abi3.so
justcode_python-0.3.0.dist-info/METADATA
justcode_python-0.3.0.dist-info/WHEEL
justcode_python-0.3.0.dist-info/RECORD
